{
  "top_greenwashing_features": [
    {
      "feature": "tons",
      "importance": 0.5752659674762629
    },
    {
      "feature": "81",
      "importance": 0.43525243268872876
    },
    {
      "feature": "verde reported",
      "importance": 0.43107538641540666
    },
    {
      "feature": "el\u00e9ctrica",
      "importance": 0.43107538641540666
    },
    {
      "feature": "el\u00e9ctrica verde",
      "importance": 0.43107538641540666
    },
    {
      "feature": "red el\u00e9ctrica",
      "importance": 0.43107538641540666
    },
    {
      "feature": "red",
      "importance": 0.43107538641540666
    },
    {
      "feature": "verde",
      "importance": 0.43107538641540666
    },
    {
      "feature": "2020 ferrovial",
      "importance": 0.39885193555247206
    },
    {
      "feature": "2022 cepsa",
      "importance": 0.38983988442939704
    },
    {
      "feature": "50",
      "importance": 0.36735202419832486
    },
    {
      "feature": "38",
      "importance": 0.3651768777416441
    },
    {
      "feature": "2018 iberdrola",
      "importance": 0.36054177956483435
    },
    {
      "feature": "2021",
      "importance": 0.3105263509220633
    },
    {
      "feature": "2020",
      "importance": 0.27014055754947575
    },
    {
      "feature": "transition tech",
      "importance": 0.2666040434115941
    },
    {
      "feature": "tech reported",
      "importance": 0.2666040434115941
    },
    {
      "feature": "tech",
      "importance": 0.2666040434115941
    },
    {
      "feature": "cepsa",
      "importance": 0.2666040434115941
    },
    {
      "feature": "cepsa transition",
      "importance": 0.2666040434115941
    }
  ],
  "top_legitimate_features": [
    {
      "feature": "mw",
      "importance": -0.8817044446134842
    },
    {
      "feature": "grenergy",
      "importance": -0.46825196386613244
    },
    {
      "feature": "grenergy renovables",
      "importance": -0.46825196386613244
    },
    {
      "feature": "renovables reported",
      "importance": -0.46825196386613244
    },
    {
      "feature": "renovables",
      "importance": -0.46825196386613244
    },
    {
      "feature": "2018 acciona",
      "importance": -0.4579799528517245
    },
    {
      "feature": "2030",
      "importance": -0.35934960567232904
    },
    {
      "feature": "45",
      "importance": -0.35692152123173376
    },
    {
      "feature": "achieving",
      "importance": -0.3365457572665079
    },
    {
      "feature": "operations",
      "importance": -0.3365457572665079
    },
    {
      "feature": "energy operations",
      "importance": -0.3365457572665079
    },
    {
      "feature": "committed",
      "importance": -0.3365457572665079
    },
    {
      "feature": "committed achieving",
      "importance": -0.3365457572665079
    },
    {
      "feature": "acciona",
      "importance": -0.3043899596315962
    },
    {
      "feature": "acciona renewables",
      "importance": -0.3043899596315962
    },
    {
      "feature": "renewables",
      "importance": -0.3043899596315962
    },
    {
      "feature": "renewables reported",
      "importance": -0.3043899596315962
    },
    {
      "feature": "2024 ferrovial",
      "importance": -0.29557453709998227
    },
    {
      "feature": "reported co\u2082",
      "importance": -0.2745582888377886
    },
    {
      "feature": "avoided",
      "importance": -0.2745582888377886
    }
  ]
}